{
  "languageserver": {
    "ccls": {
      "command": "ccls",
      "filetypes": ["c", "cc", "cpp", "c++", "objc", "objcpp"],
      "rootPatterns": [".ccls", "compile_commands.json", ".git/", ".hg/"],
      "initializationOptions": {
          "cache": {
            "directory": "/tmp/ccls"
          }
        }
    },
    "zls": {
      "command": "~/dev/zig/zls/zig-out/bin/zls",
      "filetypes": [ "zig", "zon" ]
    }
  },

  // "clangd.path": "~\\AppData\\Local\\coc\\extensions\\coc-clangd-data\\install\\18.1.3\\clangd_18.1.3\\bin\\clangd.exe",
  "diagnostic.enable": false,
  "diagnostic.enableHighlightLineNumber": false,
  "inlayHint.enable": false,

  "semanticTokens.enable": true
}

